lambkin/__init__.py
lambkin/aws.py
lambkin/exceptions.py
lambkin/lambkin.py
lambkin/metadata.py
lambkin/runtime.py
lambkin/template.py
lambkin/ux.py
lambkin/version.py
lambkin/virtualenv.py
lambkin/zip.py
lambkin-0.3.5.dist-info/DESCRIPTION.rst
lambkin-0.3.5.dist-info/METADATA
lambkin-0.3.5.dist-info/RECORD
lambkin-0.3.5.dist-info/WHEEL
lambkin-0.3.5.dist-info/entry_points.txt
lambkin-0.3.5.dist-info/metadata.json
lambkin-0.3.5.dist-info/top_level.txt
