Metadata-Version: 2.0
Name: lambkin
Version: 0.3.5
Summary: CLI tool for managing functions in AWS Lambda.
Home-page: https://github.com/jarpy/lambkin
Author: Toby McLaughlin
Author-email: toby@jarpy.net
License: UNKNOWN
Platform: UNKNOWN
Classifier: Programming Language :: Python
Classifier: Programming Language :: Python :: 2
Classifier: License :: OSI Approved :: Apache Software License
Classifier: Operating System :: POSIX
Classifier: Development Status :: 4 - Beta
Classifier: Environment :: Console
Requires-Dist: boto3
Requires-Dist: click (<7,>=6)
Requires-Dist: pystache
